infoauth/__init__.py
infoauth-1.5.data/scripts/infoauth
infoauth-1.5.dist-info/licenses/LICENSE
infoauth-1.5.dist-info/METADATA
infoauth-1.5.dist-info/WHEEL
infoauth-1.5.dist-info/top_level.txt
infoauth-1.5.dist-info/RECORD
